cg3dguru/__init__.py
cg3dguru/datatypes/__init__.py
cg3dguru/datatypes/core.py
cg3dguru/general/__init__.py
cg3dguru/general/core.py
cg3dguru/general/fbx.py
cg3d_casc_core-0.6.0.dist-info/LICENSE
cg3d_casc_core-0.6.0.dist-info/METADATA
cg3d_casc_core-0.6.0.dist-info/WHEEL
cg3d_casc_core-0.6.0.dist-info/top_level.txt
cg3d_casc_core-0.6.0.dist-info/RECORD
