Metadata-Version: 2.1
Name: cg3d-casc-core
Version: 0.6.0
Summary: A collection of classes and functions to simplify working with the Cascadeur API
Author-email: Nathaniel A <developer@3dcg.guru>
Project-URL: Homepage, https://github.com/Nathanieljla/cg3d-casc-core
Classifier: Programming Language :: Python :: 3
Classifier: Operating System :: OS Independent
Requires-Python: >=3.4
License-File: LICENSE
